genopandas/__init__.py
genopandas/core/__init__.py
genopandas/core/frame.py
genopandas/core/matrix.py
genopandas/core/tree.py
genopandas/ngs/__init__.py
genopandas/ngs/cnv.py
genopandas/ngs/rna.py
genopandas/plotting/__init__.py
genopandas/plotting/_constants.py
genopandas/plotting/base.py
genopandas/plotting/clustermap.py
genopandas/plotting/genomic.py
genopandas/sandbox/__init__.py
genopandas/sandbox/oncoplot.py
genopandas/util/__init__.py
genopandas/util/pandas_.py
genopandas-0.1.1.dist-info/DESCRIPTION.rst
genopandas-0.1.1.dist-info/LICENSE.txt
genopandas-0.1.1.dist-info/METADATA
genopandas-0.1.1.dist-info/RECORD
genopandas-0.1.1.dist-info/WHEEL
genopandas-0.1.1.dist-info/metadata.json
genopandas-0.1.1.dist-info/top_level.txt
