Metadata-Version: 2.0
Name: genopandas
Version: 0.1.1
Summary: Datastructures for manipulating, querying and plotting genomic data.
Home-page: https://github.com/jrderuiter/genopandas
Author: Julian de Ruiter
Author-email: julianderuiter@gmail.com
License: MIT license
Platform: UNKNOWN
Classifier: Development Status :: 2 - Pre-Alpha
Classifier: Intended Audience :: Developers
Classifier: License :: OSI Approved :: MIT License
Classifier: Natural Language :: English
Classifier: Programming Language :: Python :: 3.5
Requires-Dist: intervaltree
Requires-Dist: pandas
Requires-Dist: numpy
Requires-Dist: natsort
Requires-Dist: toolz
